ttlockwrapper/__init__.py
ttlockwrapper/constants.py
ttlockwrapper/ttlock.py
ttlockio-0.3.4.dist-info/LICENSE
ttlockio-0.3.4.dist-info/METADATA
ttlockio-0.3.4.dist-info/WHEEL
ttlockio-0.3.4.dist-info/entry_points.txt
ttlockio-0.3.4.dist-info/top_level.txt
ttlockio-0.3.4.dist-info/RECORD
