Metadata-Version: 2.1
Name: ttlockio
Version: 0.3.4
Summary: Python wrapper for TTLock API
Author-email: Antonio Campos <tonyldo@gmail.com>
License: MIT License
Project-URL: Homepage, https://github.com/tonyldo/ttlock.io
Keywords: ttlock,wrapper
Classifier: Programming Language :: Python :: 3
Classifier: License :: OSI Approved :: MIT License
Classifier: Operating System :: OS Independent
Requires-Python: >=3.6
License-File: LICENSE
Requires-Dist: pytest (>=5.4.1)
Requires-Dist: requests (>=2.23.0)
Requires-Dist: requests-mock (>=1.7.0)
Requires-Dist: pytest-mock
